vlcp_event_cython/__init__.py
vlcp_event_cython/event.cpython-33m.so
vlcp_event_cython/matchtree.cpython-33m.so
vlcp_event_cython/pqueue.cpython-33m.so
vlcp_event_cython-0.1.5.dist-info/DESCRIPTION.rst
vlcp_event_cython-0.1.5.dist-info/metadata.json
vlcp_event_cython-0.1.5.dist-info/top_level.txt
vlcp_event_cython-0.1.5.dist-info/WHEEL
vlcp_event_cython-0.1.5.dist-info/METADATA
vlcp_event_cython-0.1.5.dist-info/RECORD
