Metadata-Version: 2.0
Name: vlcp-event-cython
Version: 0.1.5
Summary: Cython replacement of vlcp.event
Home-page: http://github.com/hubo1016/vlcp
Author: Hu Bo
Author-email: hubo1016@126.com
License: http://www.apache.org/licenses/LICENSE-2.0
Keywords: SDN,VLCP,Openflow
Platform: UNKNOWN
